docs/argocd.md
docs/caveats.md
docs/cli.md
docs/configuration.md
docs/examples.md
docs/getting-started.md
docs/kustomize.md
docs/templates.md
examples/app_types/config/config.yml
examples/app_types/output/example/00_app_of_apps/application_01-yaml-app-example.yml
examples/app_types/output/example/00_app_of_apps/application_02-jinja2-app-example.yml
examples/app_types/output/example/00_app_of_apps/application_03-kustomize-app-example.yml
examples/app_types/output/example/00_app_of_apps/application_04-kustomize-helm-app-example.yml
examples/app_types/output/example/00_app_of_apps/application_05-argocd-managed-helm-app-example.yml
examples/app_types/output/example/00_app_of_apps/application_06-helmfile-app-example.yml
examples/app_types/output/example/01_yaml_app/configmap_example-app.yml
examples/app_types/output/example/01_yaml_app/deployment_example-app.yml
examples/app_types/output/example/01_yaml_app/service_example-app.yml
examples/app_types/output/example/02_jinja2_app/deployment_example-app.yml
examples/app_types/output/example/02_jinja2_app/service_example-app.yml
examples/app_types/output/example/03_kustomize_app/deployment_example-app.yml
examples/app_types/output/example/03_kustomize_app/service_example-app.yml
examples/app_types/output/example/04_kustomize_helm_app/deployment_hello-world.yml
examples/app_types/output/example/04_kustomize_helm_app/service_hello-world.yml
examples/app_types/output/example/04_kustomize_helm_app/serviceaccount_hello-world.yml
examples/app_types/output/example/06_helmfile_app/deployment_hello-world.yml
examples/app_types/output/example/06_helmfile_app/service_hello-world.yml
examples/app_types/output/example/06_helmfile_app/serviceaccount_hello-world.yml
examples/app_types/source/01_yaml_app/configmap_example_app.yml
examples/app_types/source/01_yaml_app/example_app.yml
examples/app_types/source/02_jinja2_app/example_app.yml.j2
examples/app_types/source/03_kustomize_app/example_app.yml.j2
make_argocd_fly-0.4.5.dist-info/licenses/LICENSE
make_argocd_fly-0.4.5.dist-info/METADATA
make_argocd_fly-0.4.5.dist-info/WHEEL
make_argocd_fly-0.4.5.dist-info/entry_points.txt
make_argocd_fly-0.4.5.dist-info/top_level.txt
make_argocd_fly-0.4.5.dist-info/RECORD
