Metadata-Version: 2.4
Name: make-argocd-fly
Version: 0.4.5
Summary: A tool to generate Kubernetes manifests from templates
Author-email: Andrei Lapin <karandash8@gmail.com>
Project-URL: Source Code, https://github.com/Karandash8/make-argocd-fly
Keywords: argocd,kustomize,jinja2
Classifier: Programming Language :: Python :: 3.11
Classifier: Programming Language :: Python :: 3.12
Requires-Python: >=3.11
License-File: LICENSE
Requires-Dist: PyYAML==6.0.3
Requires-Dist: Jinja2==3.1.6
Requires-Dist: jinja2-ansible-filters==1.3.2
Requires-Dist: yamllint==1.37.1
Requires-Dist: packaging==25.0
Requires-Dist: Deprecated==1.2.18
Dynamic: license-file
